CHANGES.txt
MANIFEST.in
README.txt
setup.cfg
setup.py
js/__init__.py
js.jquery_colorpicker.egg-info/PKG-INFO
js.jquery_colorpicker.egg-info/SOURCES.txt
js.jquery_colorpicker.egg-info/dependency_links.txt
js.jquery_colorpicker.egg-info/entry_points.txt
js.jquery_colorpicker.egg-info/namespace_packages.txt
js.jquery_colorpicker.egg-info/not-zip-safe
js.jquery_colorpicker.egg-info/requires.txt
js.jquery_colorpicker.egg-info/top_level.txt
js/jquery_colorpicker/__init__.py
js/jquery_colorpicker/test_jquery_colorpicker.txt
js/jquery_colorpicker/resources/README.txt
js/jquery_colorpicker/resources/hoge.js
js/jquery_colorpicker/resources/css/colorpicker.css
js/jquery_colorpicker/resources/css/layout.css
js/jquery_colorpicker/resources/images/blank.gif
js/jquery_colorpicker/resources/images/colorpicker_background.png
js/jquery_colorpicker/resources/images/colorpicker_hex.png
js/jquery_colorpicker/resources/images/colorpicker_hsb_b.png
js/jquery_colorpicker/resources/images/colorpicker_hsb_h.png
js/jquery_colorpicker/resources/images/colorpicker_hsb_s.png
js/jquery_colorpicker/resources/images/colorpicker_indic.gif
js/jquery_colorpicker/resources/images/colorpicker_overlay.png
js/jquery_colorpicker/resources/images/colorpicker_rgb_b.png
js/jquery_colorpicker/resources/images/colorpicker_rgb_g.png
js/jquery_colorpicker/resources/images/colorpicker_rgb_r.png
js/jquery_colorpicker/resources/images/colorpicker_select.gif
js/jquery_colorpicker/resources/images/colorpicker_submit.png
js/jquery_colorpicker/resources/images/custom_background.png
js/jquery_colorpicker/resources/images/custom_hex.png
js/jquery_colorpicker/resources/images/custom_hsb_b.png
js/jquery_colorpicker/resources/images/custom_hsb_h.png
js/jquery_colorpicker/resources/images/custom_hsb_s.png
js/jquery_colorpicker/resources/images/custom_indic.gif
js/jquery_colorpicker/resources/images/custom_rgb_b.png
js/jquery_colorpicker/resources/images/custom_rgb_g.png
js/jquery_colorpicker/resources/images/custom_rgb_r.png
js/jquery_colorpicker/resources/images/custom_submit.png
js/jquery_colorpicker/resources/images/select.png
js/jquery_colorpicker/resources/images/select2.png
js/jquery_colorpicker/resources/images/slider.png
js/jquery_colorpicker/resources/js/colorpicker.js
js/jquery_colorpicker/resources/js/eye.js
js/jquery_colorpicker/resources/js/jquery.js
