Metadata-Version: 1.0
Name: js.jquery-colorpicker
Version: 0.0.0
Summary: fanstatic jQuery color picker
Home-page: UNKNOWN
Author: Misato Takahashi
Author-email: misato@takahashi.name
License: MIT
Platform: UNKNOWN
